sqlite_orm/__init__.py
sqlite_orm/db/__init__.py
sqlite_orm/db/base_model.py
sqlite_orm/db/core.py
sqlite_orm/db/queryset.py
sqlite_orm/fields/__init__.py
sqlite_orm/fields/db_fields.py
sqlite_orm_simple-0.1.0.dist-info/licenses/License.txt
sqlite_orm_simple-0.1.0.dist-info/METADATA
sqlite_orm_simple-0.1.0.dist-info/WHEEL
sqlite_orm_simple-0.1.0.dist-info/top_level.txt
sqlite_orm_simple-0.1.0.dist-info/RECORD
