Metadata-Version: 2.4
Name: sqlite-orm-simple
Version: 0.1.0
Summary: sqlite_orm is a dependency less orm for sqlite database built with and for python
Author-email: Anwar Hosen <anwarhossene@gmail.com>
License: MIT
Project-URL: Homepage, https://github.com/code-anwarhosen/sqlite-orm
Project-URL: Issues, https://github.com/code-anwarhosen/sqlite-orm/issues
Keywords: sqlite_orm,sqlite,orm,sqlite3,sqlite3 orm
Classifier: Programming Language :: Python :: 3
Classifier: License :: OSI Approved :: MIT License
Classifier: Operating System :: OS Independent
Requires-Python: >=3.8
License-File: License.txt
Dynamic: license-file
